loggerpackage/__init__.py
loggerpackage/logger.py
loggerpackage-0.0.1.dist-info/METADATA
loggerpackage-0.0.1.dist-info/WHEEL
loggerpackage-0.0.1.dist-info/top_level.txt
loggerpackage-0.0.1.dist-info/RECORD
